toolforgeio/__init__.py
toolforgeio/arguments.py
toolforgeio/io.py
toolforgeio/manifest.py
toolforgeio-0.0.10.dist-info/LICENSE
toolforgeio-0.0.10.dist-info/METADATA
toolforgeio-0.0.10.dist-info/WHEEL
toolforgeio-0.0.10.dist-info/top_level.txt
toolforgeio-0.0.10.dist-info/RECORD
