Metadata-Version: 2.1
Name: toolforgeio
Version: 0.0.10
Summary: Library for building tools in the ToolForge Data Science tools ecosystem using Python
Author-email: Andy Boothe <andy@toolforge.io>
License: 
Project-URL: Homepage, https://github.com/toolforgeio/toolforge4py
Keywords: toolforge,toolforge.io
Classifier: License :: OSI Approved :: Apache Software License
Classifier: Programming Language :: Python
Classifier: Programming Language :: Python :: 3
Requires-Python: >=3.9
License-File: LICENSE
Requires-Dist: requests ~=2.32.0
Requires-Dist: openpyxl ~=3.1.5
Requires-Dist: pandas ~=2.2.3
Requires-Dist: PyYAML ~=6.0.2
Requires-Dist: xlrd ~=2.0.1
Requires-Dist: chardet ~=5.2.0
Requires-Dist: tomli ; python_version < "3.11"
